LICENSE.txt
MANIFEST.in
README.rst
flask_whooshalchemyplus.py
requirements.txt
setup.cfg
setup.py
Flask_WhooshAlchemyPlus.egg-info/PKG-INFO
Flask_WhooshAlchemyPlus.egg-info/SOURCES.txt
Flask_WhooshAlchemyPlus.egg-info/dependency_links.txt
Flask_WhooshAlchemyPlus.egg-info/not-zip-safe
Flask_WhooshAlchemyPlus.egg-info/requires.txt
Flask_WhooshAlchemyPlus.egg-info/top_level.txt
test/test_all.py