Metadata-Version: 1.1
Name: Flask-WhooshAlchemyPlus
Version: 0.7.3
Summary: Whoosh extension to Flask/SQLAlchemy
Home-page: https://github.com/revolution1/Flask-WhooshAlchemyPlus
Author: Revolution1
Author-email: crj93106@gmail.com
License: BSD
Platform: any
Classifier: Environment :: Web Environment
Classifier: Intended Audience :: Developers
Classifier: License :: OSI Approved :: BSD License
Classifier: Operating System :: OS Independent
Classifier: Programming Language :: Python
Classifier: Topic :: Internet :: WWW/HTTP :: Dynamic Content
Classifier: Topic :: Software Development :: Libraries :: Python Modules
